ccxt_wrapper/__init__.py
ccxt_wrapper/core.py
ccxt_wrapper/dtypes.py
ccxt_wrapper/py.typed
ccxt_wrapper/timeutils.py
ccxt_wrapper/wrapper/__init__.py
ccxt_wrapper/wrapper/all.py
ccxt_wrapper/wrapper/base.py
ccxt_wrapper/wrapper/cast.py
ccxt_wrapper/wrapper/private.py
ccxt_wrapper/wrapper/public.py
ccxt_wrapper-0.3.3.dist-info/LICENSE
ccxt_wrapper-0.3.3.dist-info/WHEEL
ccxt_wrapper-0.3.3.dist-info/METADATA
ccxt_wrapper-0.3.3.dist-info/RECORD
