Metadata-Version: 2.1
Name: ccxt-wrapper
Version: 0.3.3
Summary: A wrapper for CCXT with type hints, etc.
Home-page: https://github.com/34j/ccxt-wrapper
License: GNU General Public License v3
Author: 34j
Author-email: 55338215.34j@users.noreply.github.com
Requires-Python: >=3.8,<4.0
Classifier: Development Status :: 2 - Pre-Alpha
Classifier: Intended Audience :: Developers
Classifier: License :: Other/Proprietary License
Classifier: Natural Language :: English
Classifier: Operating System :: OS Independent
Classifier: Programming Language :: Python :: 3
Classifier: Programming Language :: Python :: 3.8
Classifier: Programming Language :: Python :: 3.9
Classifier: Programming Language :: Python :: 3.10
Classifier: Programming Language :: Python :: 3.11
Classifier: Topic :: Software Development :: Libraries
Provides-Extra: docs
Requires-Dist: attrs
Requires-Dist: ccxt
Requires-Dist: strenum
Requires-Dist: tqdm
Project-URL: Bug Tracker, https://github.com/34j/ccxt-wrapper/issues
Project-URL: Changelog, https://github.com/34j/ccxt-wrapper/blob/main/CHANGELOG.md
Project-URL: Documentation, https://ccxt-wrapper.readthedocs.io
Project-URL: Repository, https://github.com/34j/ccxt-wrapper
